pybd_oauth/__init__.py
pybd_oauth/oauth.py
pybd_oauth-1.0.3.dist-info/METADATA
pybd_oauth-1.0.3.dist-info/WHEEL
pybd_oauth-1.0.3.dist-info/top_level.txt
pybd_oauth-1.0.3.dist-info/RECORD
