Metadata-Version: 2.1
Name: pybd-oauth
Version: 1.0.3
Summary: Baidu XiongZhang Oauth Module for Python.
Home-page: https://github.com/sdkwe/pybd-oauth
Author: Hackathon
Author-email: kimi.huang@brightcells.com
License: UNKNOWN
Keywords: Baidu XiongZhang Oauth Oauth2
Platform: UNKNOWN
Classifier: License :: OSI Approved :: BSD License
Classifier: Programming Language :: Python
Classifier: Programming Language :: Python :: 2
Classifier: Programming Language :: Python :: 2.6
Classifier: Programming Language :: Python :: 2.7
Classifier: Programming Language :: Python :: 3
Classifier: Programming Language :: Python :: 3.2
Classifier: Programming Language :: Python :: 3.3
Classifier: Programming Language :: Python :: 3.4
Classifier: Topic :: Software Development :: Libraries :: Python Modules
Requires-Dist: pybd-base (>=1.0.2)
Requires-Dist: shortuuid
